setup.py
lewaa/__init__.py
lewaa/lewaa.py
lewaa.egg-info/PKG-INFO
lewaa.egg-info/SOURCES.txt
lewaa.egg-info/dependency_links.txt
lewaa.egg-info/not-zip-safe
lewaa.egg-info/top_level.txt