Metadata-Version: 2.1
Name: lewaa
Version: 0.0.1
Summary: Lewaa Dataframe
Author: Abdul Qadeer
Author-email: imaqafridi@gmail.com
License: UNKNOWN
Platform: UNKNOWN
